packagetools/__init__.py
packagetools/metadata.py
packagetools/utils.py
packagetools-0.1.0.dist-info/DESCRIPTION.rst
packagetools-0.1.0.dist-info/METADATA
packagetools-0.1.0.dist-info/RECORD
packagetools-0.1.0.dist-info/WHEEL
packagetools-0.1.0.dist-info/metadata.json
packagetools-0.1.0.dist-info/top_level.txt
