Metadata-Version: 2.0
Name: packagetools
Version: 0.1.0
Summary: A toolset for submitting packages to PyPi.
Home-page: https://github.com/lionheart/packagetools
Author: Dan Loewenherz
Author-email: dan@lionheartsw.com
License: Apache 2.0
Download-URL: https://github.com/lionheart/packagetools/tarball/0.1.0
Keywords: package pypi
Platform: UNKNOWN
Classifier: Development Status :: 5 - Production/Stable
Classifier: Environment :: Console
Classifier: Intended Audience :: Developers
Classifier: License :: OSI Approved :: Apache Software License
Classifier: Natural Language :: English
Classifier: Operating System :: OS Independent
Classifier: Programming Language :: Python :: 2.7
Classifier: Programming Language :: Python :: 3.5
Classifier: Programming Language :: Python :: 3.6
Classifier: Programming Language :: Python
Classifier: Topic :: Internet :: WWW/HTTP :: Dynamic Content :: CGI Tools/Libraries
Classifier: Topic :: Software Development :: Libraries :: Python Modules
Classifier: Topic :: Utilities
